{"cpu_time": 0, "total_cpu_time": null, "wallclock_time": 1.5735626220703125e-05, "evaluations": 0, "cost": 2147483648, "incumbent": ["balancing:strategy=''none''", "categorical_encoding:__choice__=''one_hot_encoding''", "classifier:__choice__=''random_forest''", "imputation:strategy=''mean''", "preprocessor:__choice__=''no_preprocessing''", "rescaling:__choice__=''standardize''", "categorical_encoding:one_hot_encoding:use_minimum_fraction=''True''", "classifier:random_forest:bootstrap=''True''", "classifier:random_forest:criterion=''gini''", "classifier:random_forest:max_depth=''None''", "classifier:random_forest:max_features='0.5'", "classifier:random_forest:max_leaf_nodes=''None''", "classifier:random_forest:min_impurity_decrease='0.0'", "classifier:random_forest:min_samples_leaf='1'", "classifier:random_forest:min_samples_split='2'", "classifier:random_forest:min_weight_fraction_leaf='0.0'", "classifier:random_forest:n_estimators='100'", "categorical_encoding:one_hot_encoding:minimum_fraction='0.01'"]}
{"cpu_time": 1.876598834991455, "total_cpu_time": null, "wallclock_time": 1.919541358947754, "evaluations": 3, "cost": 0.017977528089887618, "incumbent": ["balancing:strategy=''none''", "categorical_encoding:__choice__=''no_encoding''", "classifier:__choice__=''k_nearest_neighbors''", "imputation:strategy=''mean''", "preprocessor:__choice__=''select_rates''", "rescaling:__choice__=''normalize''", "classifier:k_nearest_neighbors:n_neighbors='4'", "classifier:k_nearest_neighbors:p='2'", "classifier:k_nearest_neighbors:weights=''uniform''", "preprocessor:select_rates:alpha='0.1'", "preprocessor:select_rates:mode=''fpr''", "preprocessor:select_rates:score_func=''chi2''"]}
{"cpu_time": 2.833681583404541, "total_cpu_time": null, "wallclock_time": 2.8894639015197754, "evaluations": 4, "cost": 0.011235955056179803, "incumbent": ["balancing:strategy=''none''", "categorical_encoding:__choice__=''no_encoding''", "classifier:__choice__=''liblinear_svc''", "imputation:strategy=''most_frequent''", "preprocessor:__choice__=''kitchen_sinks''", "rescaling:__choice__=''normalize''", "classifier:liblinear_svc:C='6.556190405302503'", "classifier:liblinear_svc:dual=''False''", "classifier:liblinear_svc:fit_intercept=''True''", "classifier:liblinear_svc:intercept_scaling='1'", "classifier:liblinear_svc:loss=''squared_hinge''", "classifier:liblinear_svc:multi_class=''ovr''", "classifier:liblinear_svc:penalty=''l2''", "classifier:liblinear_svc:tol='0.0007318628304090555'", "preprocessor:kitchen_sinks:gamma='3.560201454218397'", "preprocessor:kitchen_sinks:n_components='948'"]}
